shopicli/__init__.py
shopicli/__main__.py
shopicli/_config.py
shopicli/_output.py
shopicli/_types.py
shopicli/_utils.py
shopicli/cli.py
shopicli/client.py
ShopiCLI-0.1.1.dist-info/METADATA
ShopiCLI-0.1.1.dist-info/WHEEL
ShopiCLI-0.1.1.dist-info/entry_points.txt
ShopiCLI-0.1.1.dist-info/top_level.txt
ShopiCLI-0.1.1.dist-info/RECORD
