Metadata-Version: 2.1
Name: ShopiCLI
Version: 0.1.1
Summary: Shopify command-line client
Home-page: https://github.com/rshk/shopicli
Author: Samuele Santi
Author-email: samuele.santi@reinventsoftware.io
License: BSD License
Platform: UNKNOWN
Classifier: License :: OSI Approved :: BSD License
Classifier: Programming Language :: Python :: 3.6
Classifier: Programming Language :: Python :: 3.7
Classifier: Programming Language :: Python :: 3 :: Only
Requires-Dist: click (>=7)
Requires-Dist: requests (>=2)
Requires-Dist: nicelog (>=0.3)
Requires-Dist: pygments
